pt_at_qr_code/__init__.py
pt_at_qr_code/exceptions.py
pt_at_qr_code/field_registry.py
pt_at_qr_code/parser.py
python_pt_at_qr_code-0.0.3.dist-info/LICENSE
python_pt_at_qr_code-0.0.3.dist-info/METADATA
python_pt_at_qr_code-0.0.3.dist-info/WHEEL
python_pt_at_qr_code-0.0.3.dist-info/top_level.txt
python_pt_at_qr_code-0.0.3.dist-info/RECORD
