Metadata-Version: 2.1
Name: python-pt-at-qr-code
Version: 0.0.3
Summary: Portuguese fiscal documents QR Code library
Home-page: https://github.com/tavaresb/python-pt-at-qr-code
Author: Bruno Tavares
Author-email: tavares.b@gmail.com
License: UNKNOWN
Project-URL: Bug Tracker, https://github.com/tavaresb/python-pt-at-qr-code/issues
Platform: UNKNOWN
Classifier: Programming Language :: Python :: 3
Classifier: License :: OSI Approved :: MIT License
Classifier: Operating System :: OS Independent
Requires-Python: >=3.6
License-File: LICENSE
